docbench.py
setup.py
docbench.egg-info/PKG-INFO
docbench.egg-info/SOURCES.txt
docbench.egg-info/dependency_links.txt
docbench.egg-info/requires.txt
docbench.egg-info/top_level.txt