Metadata-Version: 1.1
Name: docbench
Version: 1.0.0-alpha.1
Summary: Benchmark with doctest
Home-page: https://github.com/boisgera/docbench
Author: Sébastien Boisgérault
Author-email: Sebastien.Boisgerault@mines-paristech.fr
License: MIT License
Platform: UNKNOWN
Classifier: Intended Audience :: Developers
Classifier: Operating System :: OS Independent
Classifier: Programming Language :: Python :: 2.7
Classifier: License :: OSI Approved :: MIT License
Classifier: Topic :: Software Development :: Libraries :: Python Modules
Classifier: Topic :: Software Development :: Testing
Classifier: Topic :: System :: Benchmark
